zarf/__init__.py
zarf/tests.py
zarf/__pycache__/__init__.cpython-313.pyc
zarf/__pycache__/tests.cpython-313-pytest-8.3.5.pyc
zarf-0.0.2.dist-info/licenses/LICENSE
zarf-0.0.2.dist-info/METADATA
zarf-0.0.2.dist-info/WHEEL
zarf-0.0.2.dist-info/top_level.txt
zarf-0.0.2.dist-info/RECORD
