Metadata-Version: 2.4
Name: zarf
Version: 0.0.2
Summary: A simple Dependency Container library
Home-page: https://github.com/hadi77ir/zarf
Author-email: Mohammad Hadi Hosseinpour <wp.parsi@gmail.com>
License-Expression: MIT
Project-URL: Homepage, https://github.com/hadi77ir/zarf
Project-URL: Issues, https://github.com/hadi77ir/zarf/issues
Classifier: Programming Language :: Python :: 3
Classifier: Operating System :: OS Independent
Requires-Python: >=3.6
License-File: LICENSE
Dynamic: home-page
Dynamic: license-file
Dynamic: requires-python
